[
  {
    "model": "p100",
    "name": "CS@ MEETION GAMING MOUSE PAD MT P100 MAT LONGER",
    "store": "Banana",
    "brand": "Meetion",
    "category": "Mousepad",
    "tag": "Gaming",
    "data": [
      {
        "name": "CS@ MEETION GAMING MOUSE PAD MT P100 MAT LONGER",
        "price": 199,
        "href": "https://www.bnn.in.th/th/p/gaming-gear/pc-gaming-accessories/gaming-mouse-pad/cs-at-meetion-gaming-mouse-pad-mt-p100-mat-longer-6970344731394_zpm5ez",
        "image": "https://media-cdn.bnn.in.th/123615/MeeTion-Gaming-Mouse-Pad-MT-P100-02-square_medium.jpg",
        "spec": {
          "dimension": "7.9 x 3.45 x 0.5 cm.",
          "material": "Non-slip Rubber Base"
        }
      }
    ]
  },
  {
    "model": "p110",
    "name": "CS@ MEETION GAMING MOUSE PAD MT P110 MAT SQUARE",
    "store": "Banana",
    "brand": "Meetion",
    "category": "Mousepad",
    "tag": "Gaming",
    "data": [
      {
        "name": "CS@ MEETION GAMING MOUSE PAD MT P110 MAT SQUARE",
        "price": 119,
        "href": "https://www.bnn.in.th/th/p/gaming-gear/pc-gaming-accessories/gaming-mouse-pad/cs-at-meetion-gaming-mouse-pad-mt-p110-mat-square-6970344731370_r0836z",
        "image": "https://media-cdn.bnn.in.th/104536/6970344731370-6-square_medium.jpg",
        "spec": {
          "dimension": "35 x 6.5 x 6.5 cm.",
          "material": "Non-slip Rubber Base"
        }
      }
    ]
  },
  {
    "model": "p010",
    "name": "CS@ MEETION GAMING MOUSE PAD MT- P010 RGB BACKLIT",
    "store": "Banana",
    "brand": "Meetion",
    "category": "Mousepad",
    "tag": "Gaming",
    "data": [
      {
        "name": "CS@ MEETION GAMING MOUSE PAD MT- P010 RGB BACKLIT",
        "price": 590,
        "href": "https://www.bnn.in.th/th/p/gaming-gear/pc-gaming-accessories/gaming-mouse-pad/cs-at-meetion-gaming-mouse-pad-mt-p010-rgb-backlit-6970344731509_d4e14z",
        "image": "https://media-cdn.bnn.in.th/123603/MeeTion-Gaming-Mouse-Pad-MT--P010-02-square_medium.jpg",
        "spec": {
          "dimension": "35 x 25 x 0.5 cm.",
          "material": "Non-slip Rubber Base"
        }
      }
    ]
  },
  {
    "model": "mp292",
    "name": "FANTECH GAMING MOUSE PAD MP292",
    "store": "Banana",
    "brand": "Fantech",
    "category": "Mousepad",
    "tag": "Gaming",
    "data": [
      {
        "name": "FANTECH GAMING MOUSE PAD MP292 BLACK",
        "price": 60,
        "href": "https://www.bnn.in.th/th/p/gaming-gear/pc-gaming-accessories/gaming-mouse-pad/fantech-gaming-mouse-pad-mp292-black-6912654682265_dlmkpz",
        "image": "https://media-cdn.bnn.in.th/47944/6912654682265-3-square_medium.jpg",
        "spec": { "dimension": "29.00 x 25.00 x 0.30 cm.", "material": "N/A" }
      }
    ]
  },
  {
    "model": "mp902",
    "name": "FANTECH GAMING MOUSE PAD MP902",
    "store": "Banana",
    "brand": "Fantech",
    "category": "Mousepad",
    "tag": "Gaming",
    "data": [
      {
        "name": "FANTECH GAMING MOUSE PAD MP902 BLACK",
        "price": 200,
        "href": "https://www.bnn.in.th/th/p/gaming-gear/pc-gaming-accessories/gaming-mouse-pad/fantech-gaming-mouse-pad-mp902-black-6912654682267_dyq3wz",
        "image": "https://media-cdn.bnn.in.th/47954/6912654682267-5-square_medium.jpg",
        "spec": { "dimension": "90 x 30 x 0.30 cm.", "material": "N/A" }
      }
    ]
  },
  {
    "model": "furysprospeed",
    "name": "HYPER X GAMING MOUSE PAD FURY S PRO SPEED",
    "store": "Banana",
    "brand": "Hyper x",
    "category": "Mousepad",
    "tag": "Gaming",
    "data": [
      {
        "name": "HYPER X GAMING MOUSE PAD FURY S PRO SPEED EDITION EXTENDED",
        "price": 990,
        "href": "https://www.bnn.in.th/th/p/gaming-gear/pc-gaming-accessories/gaming-mouse-pad/hyper-x-gaming-mouse-pad-fury-s-pro-speed-edition-extended-740617274462_zoo2xz",
        "image": "https://media-cdn.bnn.in.th/53856/HyperX-Gaming-Mouse-Pad-FuryS-Pro-Speed-Edition-Extended-01-square_medium.jpg",
        "spec": { "dimension": "90 x 40 x 0.3 cm.", "material": "Rubber" }
      }
    ]
  },
  {
    "model": "furysprospeed",
    "name": "HYPER X GAMING MOUSE PAD FURY S PRO SPEED",
    "store": "Banana",
    "brand": "Hyper x",
    "category": "Mousepad",
    "tag": "Gaming",
    "data": [
      {
        "name": "HYPER X GAMING MOUSE PAD FURY S PRO SPEED EXTENDED",
        "price": 990,
        "href": "https://www.bnn.in.th/th/p/gaming-gear/pc-gaming-accessories/gaming-mouse-pad/hyper-x-gaming-mouse-pad-fury-s-pro-speed-extended-740617267082_d4m65d",
        "image": "https://media-cdn.bnn.in.th/53729/Hyper-X-Gaming-Mouse-Pad-Fury-S-Pro-Speed-Extended-3-square_medium.jpg",
        "spec": { "dimension": "90 x 40 x 0.3 cm.", "material": "Rubber" }
      }
    ]
  },
  {
    "model": "",
    "name": "",
    "store": "Banana",
    "brand": "Neolution",
    "category": "Mousepad",
    "tag": "Gaming",
    "data": [
      {
        "name": "NEOLUTION GAMING MOUSE PAD SPEED M SIZE",
        "price": 60,
        "href": "https://www.bnn.in.th/th/p/gaming-gear/pc-gaming-accessories/gaming-mouse-pad/neolution-gaming-mouse-pad-speed-m-size-8887210015640_dm0mmn",
        "image": "https://media-cdn.bnn.in.th/90121/neolution-gaming-mouse-pad-speed-m-size-1-square_medium.jpg",
        "spec": { "dimension": "32 x 27 x 0.30 cm.", "material": "Rubber Base" }
      }
    ]
  },
  {
    "model": "",
    "name": "",
    "store": "Banana",
    "brand": "Neolution",
    "category": "Mousepad",
    "tag": "Gaming",
    "data": [
      {
        "name": "NEOLUTION GAMING MOUSE PAD SPEED SIZE L",
        "price": 250,
        "href": "https://www.bnn.in.th/th/p/gaming-gear/pc-gaming-accessories/gaming-mouse-pad/neolution-gaming-mouse-pad-speed-size-l-8887210010652_zowpp6",
        "image": "https://media-cdn.bnn.in.th/90077/8887210010652-4-square_medium.jpg",
        "spec": {
          "dimension": "40 x 32 x 0.30",
          "material": "Rubber Top Cover Fabric Coation"
        }
      }
    ]
  },
  {
    "model": "",
    "name": "",
    "store": "Banana",
    "brand": "Neolution",
    "category": "Mousepad",
    "tag": "Gaming",
    "data": [
      {
        "name": "NEOLUTION GAMING MOUSE PAD SPEED XXL SIZE",
        "price": 280,
        "href": "https://www.bnn.in.th/th/p/gaming-gear/pc-gaming-accessories/gaming-mouse-pad/neolution-gaming-mouse-pad-speed-xxl-size-8887210015657_zvl00k",
        "image": "https://media-cdn.bnn.in.th/90125/8887210015657-1-square_medium.jpg",
        "spec": { "dimension": "80 x 30 x 0.30 cm.", "material": "Rubber Base" }
      }
    ]
  },
  {
    "model": "g5",
    "name": "ONIKUMA GAMING MOUSE PAD G5 RGB",
    "store": "Banana",
    "brand": "Onikuma",
    "category": "Mousepad",
    "tag": "Gaming",
    "data": [
      {
        "name": "ONIKUMA GAMING MOUSE PAD G5 RGB PINK",
        "price": 490,
        "href": "https://www.bnn.in.th/th/p/gaming-gear/pc-gaming-accessories/gaming-mouse-pad/onikuma-gaming-mouse-pad-g5-rgb-pink-6972470561470_r62o68",
        "image": "https://media-cdn.bnn.in.th/137324/Mouse-Pad-G5-RGB-02-square_medium.jpg",
        "spec": { "dimension": "80 x 30 x 0.4 cm.", "material": "Rubber base" }
      }
    ]
  },
  {
    "model": "g6",
    "name": "ONIKUMA GAMING MOUSE PAD G6",
    "store": "Banana",
    "brand": "Onikuma",
    "category": "Mousepad",
    "tag": "Gaming",
    "data": [
      {
        "name": "ONIKUMA GAMING MOUSE PAD G6 RGB BLACK",
        "price": 490,
        "href": "https://www.bnn.in.th/th/p/gaming-gear/pc-gaming-accessories/gaming-mouse-pad/onikuma-gaming-mouse-pad-g6-rgb-black-6972470561487_rq81j2",
        "image": "https://media-cdn.bnn.in.th/137347/Mouse-Pad-G6-RGB-01-square_medium.jpg",
        "spec": { "dimension": "80 x 30 x 0.4 cm.", "material": "Rubber base" }
      }
    ]
  },
  {
    "model": "sakura",
    "name": "ONIKUMA GAMING SAKURA MOUSEPAD",
    "store": "Banana",
    "brand": "Onikuma",
    "category": "Mousepad",
    "tag": "Gaming",
    "data": [
      {
        "name": "ONIKUMA GAMING SAKURA MOUSEPAD PINK",
        "price": 199,
        "href": "https://www.bnn.in.th/th/p/gaming-gear/pc-gaming-accessories/gaming-mouse-pad/onikuma-gaming-sakura-mousepad-pink-1122022154899_dll2yn",
        "image": "https://media-cdn.bnn.in.th/128971/Onikuma-Gaming-Sakura-Mousepad-01-square_medium.jpg",
        "spec": { "dimension": "78x 30 x0.3 cm.", "material": "Rubber base" }
      }
    ]
  },
  {
    "model": "lightacrylic",
    "name": "PHILIPS GAMING MOUSE PAD LIGHT ACRYLIC",
    "store": "Banana",
    "brand": "Philips",
    "category": "Mousepad",
    "tag": "Gaming",
    "data": [
      {
        "name": "PHILIPS GAMING MOUSE PAD LIGHT ACRYLIC SIZE L WITH 1.8M CABLE BLACK (SPL7304RGB)",
        "price": 390,
        "href": "https://www.bnn.in.th/th/p/gaming-gear/pc-gaming-accessories/gaming-mouse-pad/philips-gaming-mouse-pad-light-acrylic-size-l-with-18m-cable-black-spl7304rgb-8712581763022_zow3yk",
        "image": "https://media-cdn.bnn.in.th/68219/Philips-Gaming-Mouse-Pad-Light-Acrylic-Size-L-SPL7304RGB-04-square_medium.jpg",
        "spec": {
          "dimension": "35.2 x 25.5 x 0.5 cm.",
          "material": "Non-slip Rubber Base"
        }
      }
    ]
  },
  {
    "model": "lightcontrol",
    "name": "PHILIPS GAMING MOUSE PAD LIGHT CONTROL",
    "store": "Banana",
    "brand": "Philips",
    "category": "Mousepad",
    "tag": "Gaming",
    "data": [
      {
        "name": "PHILIPS GAMING MOUSE PAD LIGHT CONTROL SIZE M USB HUB ADDITIONAL WITH 1.8M CABLE BLACK (SPL7204RGB)",
        "price": 590,
        "href": "https://www.bnn.in.th/th/p/gaming-gear/pc-gaming-accessories/gaming-mouse-pad/philips-gaming-mouse-pad-light-control-size-m-usb-hub-additional-with-18m-cable-black-spl7204rgb-8712581763473_zg83yq",
        "image": "https://media-cdn.bnn.in.th/68237/Philips-Gaming-Mouse-Pad-Light-Control-Size-M-USB-HUB-SPL7204RGB-04-square_medium.jpg",
        "spec": {
          "dimension": "80 x 30 x 0.4 cm.",
          "material": "Non-slip Rubber Base"
        }
      }
    ]
  },
  {
    "model": "lightcontrol",
    "name": "PHILIPS GAMING MOUSE PAD LIGHT CONTROL",
    "store": "Banana",
    "brand": "Philips",
    "category": "Mousepad",
    "tag": "Gaming",
    "data": [
      {
        "name": "PHILIPS GAMING MOUSE PAD LIGHT CONTROL SIZE M WITH 1.8M CABLE BLACK (SPL7104RGB)",
        "price": 550,
        "href": "https://www.bnn.in.th/th/p/gaming-gear/pc-gaming-accessories/gaming-mouse-pad/philips-gaming-mouse-pad-light-control-size-m-with-18m-cable-black-spl7104rgb-8712581763466_d41xn2",
        "image": "https://media-cdn.bnn.in.th/68228/Philips-Gaming-Mouse-Pad-Light-Control-Size-M-SPL7104RGB-05-square_medium.jpg",
        "spec": {
          "dimension": "80 x 30.5 x 0.4 cm.",
          "material": "Non-slip Rubber Base"
        }
      }
    ]
  },
  {
    "model": "sphexv3",
    "name": "RAZER GAMING MOUSE PAD SPHEX V3 LARGE",
    "store": "Banana",
    "brand": "Razer",
    "category": "Mousepad",
    "tag": "Gaming",
    "data": [
      {
        "name": "RAZER GAMING MOUSE PAD SPHEX V3 LARGE BLACK",
        "price": 899,
        "href": "https://www.bnn.in.th/th/p/gaming-gear/pc-gaming-accessories/gaming-mouse-pad/razer-gaming-mouse-pad-sphex-v3-large-black-8886419319191_dm0ynl",
        "image": "https://media-cdn.bnn.in.th/120019/Razer-Gaming-Mouse-Pad-Sphex-V3-Large-Black-1-square_medium.jpg",
        "spec": {
          "dimension": "45 cm. / 1.772” x 40 cm. / 1.574 cm.",
          "material": "ADHESIVE BASE"
        }
      }
    ]
  },
  {
    "model": "mt317",
    "name": "SIGNO GAMING MOUSE MAT ABSTRA-2 MT-317",
    "store": "Banana",
    "brand": "Signo",
    "category": "Mousepad",
    "tag": "Gaming",
    "data": [
      {
        "name": "SIGNO GAMING MOUSE MAT ABSTRA-2 MT-317 SPEED EDITION (770 X 295 X 4 MM.)",
        "price": 140,
        "href": "https://www.bnn.in.th/th/p/gaming-gear/pc-gaming-accessories/gaming-mouse-pad/signo-gaming-mouse-mat-abstra-2-mt-317-speed-edition-770-x-295-x-4-mm-8636569403208_zwle6m",
        "image": "https://media-cdn.bnn.in.th/67146/8636569403208-1-square_medium.jpg",
        "spec": {
          "dimension": "77 x 29.50 x 0.40 cm.",
          "material": "Non-slip Rubber Base"
        }
      }
    ]
  },
  {
    "model": "mt328",
    "name": "SIGNO GAMING MOUSE MAT AREAS-1 MT-328",
    "store": "Banana",
    "brand": "Signo",
    "category": "Mousepad",
    "tag": "Gaming",
    "data": [
      {
        "name": "SIGNO GAMING MOUSE MAT AREAS-1 MT-328 BLACK",
        "price": 250,
        "href": "https://www.bnn.in.th/th/p/gaming-gear/pc-gaming-accessories/gaming-mouse-pad/signo-gaming-mouse-mat-areas-1-mt-328-black-8513227309419_r620gm",
        "image": "https://media-cdn.bnn.in.th/130612/Mouse-Mat-Areas-1-MT-328-Black-01-square_medium.jpg",
        "spec": {
          "dimension": "77.0 x 29.5 x 0.4 cm.",
          "material": "Non-slip Rubber Base"
        }
      }
    ]
  },
  {
    "model": "mt329",
    "name": "SIGNO GAMING MOUSE MAT AREAS-2 MT-329",
    "store": "Banana",
    "brand": "Signo",
    "category": "Mousepad",
    "tag": "Gaming",
    "data": [
      {
        "name": "SIGNO GAMING MOUSE MAT AREAS-2 MT-329 BLACK",
        "price": 220,
        "href": "https://www.bnn.in.th/th/p/gaming-gear/pc-gaming-accessories/gaming-mouse-pad/signo-gaming-mouse-mat-areas-2-mt-329-black-8554920394883_rq824x",
        "image": "https://media-cdn.bnn.in.th/130654/Mouse-Mat-Areas-2-MT-329-01-square_medium.jpg",
        "spec": {
          "dimension": "45.0 x 40.0 x 0.4 cm.",
          "material": "Non-slip Rubber Base"
        }
      }
    ]
  },
  {
    "model": "mt330",
    "name": "SIGNO GAMING MOUSE MAT AREAS-3 MT-330",
    "store": "Banana",
    "brand": "Signo",
    "category": "Mousepad",
    "tag": "Gaming",
    "data": [
      {
        "name": "SIGNO GAMING MOUSE MAT AREAS-3 MT-330 BLACK",
        "price": 290,
        "href": "https://www.bnn.in.th/th/p/gaming-gear/pc-gaming-accessories/gaming-mouse-pad/signo-gaming-mouse-mat-areas-3-mt-330-black-8143238492802_z970qe",
        "image": "https://media-cdn.bnn.in.th/130979/Areas-3-MT-330-Black-01-square_medium.jpg",
        "spec": {
          "dimension": "90 x 40 x 0.3 cm.",
          "material": "Non-slip Rubber Base"
        }
      }
    ]
  },
  {
    "model": "mt310",
    "name": "SIGNO GAMING MOUSE MAT CORVUS MT-310",
    "store": "Banana",
    "brand": "Signo",
    "category": "Mousepad",
    "tag": "Gaming",
    "data": [
      {
        "name": "SIGNO GAMING MOUSE MAT CORVUS MT-310 SPEED EDITION (320 X 240 X 4 MM.)",
        "price": 71,
        "href": "https://www.bnn.in.th/th/p/gaming-gear/pc-gaming-accessories/gaming-mouse-pad/signo-gaming-mouse-mat-corvus-mt-310-speed-edition-320-x-240-x-4-mm-8231194782942_z977ve",
        "image": "https://media-cdn.bnn.in.th/63403/8231194782942-2-square_medium.jpg",
        "spec": {
          "dimension": "32 x 24 x 0.40 cm.",
          "material": "Non-slip Rubber Base"
        }
      }
    ]
  },
  {
    "model": "mt321",
    "name": "SIGNO GAMING MOUSE MAT ICONIC-2 MT-321",
    "store": "Banana",
    "brand": "Signo",
    "category": "Mousepad",
    "tag": "Gaming",
    "data": [
      {
        "name": "SIGNO GAMING MOUSE MAT ICONIC-2 MT-321 SPEED EDITION (770 X 295 X 4 MM.)",
        "price": 180,
        "href": "https://www.bnn.in.th/th/p/gaming-gear/pc-gaming-accessories/gaming-mouse-pad/signo-gaming-mouse-mat-iconic-2-mt-321-speed-edition-770-x-295-x-4-mm-8353391028927_dy66x2",
        "image": "https://media-cdn.bnn.in.th/63605/8353391028927-1-square_medium.jpg",
        "spec": {
          "dimension": "77 x 29.50 x 0.40 cm.",
          "material": "Non-slip Rubber Base"
        }
      }
    ]
  },
  {
    "model": "mt323",
    "name": "SIGNO GAMING MOUSE MAT LED CHROMA-1 MT-323",
    "store": "Banana",
    "brand": "Signo",
    "category": "Mousepad",
    "tag": "Gaming",
    "data": [
      {
        "name": "SIGNO GAMING MOUSE MAT LED CHROMA-1 MT-323 SPEED EDITION (360 X 260 X 3 MM.)",
        "price": 350,
        "href": "https://www.bnn.in.th/th/p/gaming-gear/pc-gaming-accessories/gaming-mouse-pad/signo-gaming-mouse-mat-iconic-3-mt-322-speed-edition-450-x-400-x-4-mm-8387921656304_d22292https://www.bnn.in.th/th/p/gaming-gear/pc-gaming-accessories/gaming-mouse-pad/signo-gaming-mouse-mat-led-chroma-1-mt-323-speed-edition-360-x-260-x-3-mm-8153329058626_z32v06",
        "image": "https://media-cdn.bnn.in.th/61960/8153329058626-1-square_medium.jpg",
        "spec": {
          "dimension": "36 x 26 x 0.30 cm.",
          "material": "Non-slip Rubber Base"
        }
      }
    ]
  },
  {
    "model": "mt324",
    "name": "SIGNO GAMING MOUSE MAT LED CHROMA-2 MT-324",
    "store": "Banana",
    "brand": "Signo",
    "category": "Mousepad",
    "tag": "Gaming",
    "data": [
      {
        "name": "SIGNO GAMING MOUSE MAT LED CHROMA-2 MT-324 SPEED EDITION (770 X 295 X 4 MM.)",
        "price": 340,
        "href": "https://www.bnn.in.th/th/p/gaming-gear/pc-gaming-accessories/gaming-mouse-pad/signo-gaming-mouse-mat-led-chroma-2-mt-324-speed-edition-770-x-295-x-4-mm-8154590213394_dy6yk4",
        "image": "https://media-cdn.bnn.in.th/61964/8154590213394-1-square_medium.jpg",
        "spec": {
          "dimension": "77 x 29.50 x 0.40 cm.",
          "material": "Non-slip Rubber Base"
        }
      }
    ]
  },
  {
    "model": "mt305",
    "name": "SIGNO GAMING MOUSE MAT MT-305",
    "store": "Banana",
    "brand": "Signo",
    "category": "Mousepad",
    "tag": "Gaming",
    "data": [
      {
        "name": "SIGNO GAMING MOUSE MAT MT-305 B GROONE BLACK/BLUE",
        "price": 170,
        "href": "https://www.bnn.in.th/th/p/gaming-gear/pc-gaming-accessories/gaming-mouse-pad/signo-gaming-mouse-mat-mt-305-b-groone-blackblue-8117830294485_d1148l",
        "image": "https://media-cdn.bnn.in.th/123343/Signo-Gaming-Mouse-Mat-Mt-305-B-Groone-BlackBlue-1-square_medium.jpg",
        "spec": {
          "dimension": "77 x 29.5 x 0.3 cm.",
          "material": "Non-slip Rubber Base"
        }
      }
    ]
  },
  {
    "model": "mt306",
    "name": "SIGNO GAMING MOUSE MAT MT-306",
    "store": "Banana",
    "brand": "Signo",
    "category": "Mousepad",
    "tag": "Gaming",
    "data": [
      {
        "name": "SIGNO GAMING MOUSE MAT MT-306 P SPEED",
        "price": 170,
        "href": "https://www.bnn.in.th/th/p/gaming-gear/pc-gaming-accessories/gaming-mouse-pad/signo-gaming-mouse-mat-mt-306-p-speed-8113640579231_zvlnop",
        "image": "https://media-cdn.bnn.in.th/59810/SIGNO-Gaming-3-square_medium.jpg",
        "spec": {
          "dimension": "77 x 29.5 x 0.3 cm.",
          "material": "Non-slip Rubber Base"
        }
      }
    ]
  },
  {
    "model": "mt308",
    "name": "SIGNO GAMING MOUSE MAT SPEED MT-308",
    "store": "Banana",
    "brand": "Signo",
    "category": "Mousepad",
    "tag": "Gaming",
    "data": [
      {
        "name": "SIGNO GAMING MOUSE MAT SPEED MT-308 (770 X 295 X 3 MM.)",
        "price": 162,
        "href": "https://www.bnn.in.th/th/p/gaming-gear/pc-gaming-accessories/gaming-mouse-pad/signo-gaming-mouse-mat-speed-mt-308-770-x-295-x-3-mm-8615520588765_ze0164",
        "image": "https://media-cdn.bnn.in.th/67114/8615520588765-1-square_medium.jpg",
        "spec": {
          "dimension": "77 x 29.50 x 0.30 cm.",
          "material": "Non-slip Rubber Base"
        }
      }
    ]
  },
  {
    "model": "mt309",
    "name": "SIGNO GAMING MOUSE MAT SPEED MT-309",
    "store": "Banana",
    "brand": "Signo",
    "category": "Mousepad",
    "tag": "Gaming",
    "data": [
      {
        "name": "SIGNO GAMING MOUSE MAT SPEED MT-309 (770 X 295 X 3 MM.)",
        "price": 162,
        "href": "https://www.bnn.in.th/th/p/gaming-gear/pc-gaming-accessories/gaming-mouse-pad/signo-gaming-mouse-mat-speed-mt-309-770-x-295-x-3-mm-8612821183521_dkoewj",
        "image": "https://media-cdn.bnn.in.th/67110/8612821183521-1-square_medium.jpg",
        "spec": {
          "dimension": "77 x 29.50 x 0.30 cm.",
          "material": "Non-slip Rubber Base"
        }
      }
    ]
  },
  {
    "model": "mt327",
    "name": "SIGNO GAMING MOUSE MAT SPEEDER MT-327",
    "store": "Banana",
    "brand": "Signo",
    "category": "Mousepad",
    "tag": "Gaming",
    "data": [
      {
        "name": "SIGNO GAMING MOUSE MAT SPEEDER MT-327 BLACK",
        "price": 230,
        "href": "https://www.bnn.in.th/th/p/gaming-gear/pc-gaming-accessories/gaming-mouse-pad/signo-gaming-mouse-mat-speeder-mt-327-black-8251936632953_ze0064",
        "image": "https://media-cdn.bnn.in.th/63451/Signo-Gaming-Mouse-Mat-Speeder-MT-327-Black-3-square_medium.jpg",
        "spec": {
          "dimension": "90.0 x 40.0 x 0.3 cm.",
          "material": "Non-slip Rubber Base"
        }
      }
    ]
  },
  {
    "model": "wr500",
    "name": "SIGNO WRIST PAD ZUPLEX WR-500",
    "store": "Banana",
    "brand": "Signo",
    "category": "Mousepad",
    "tag": "Gaming",
    "data": [
      {
        "name": "SIGNO WRIST PAD ZUPLEX WR-500 BLACK",
        "price": 180,
        "href": "https://www.bnn.in.th/th/p/it-accessories/mouse-and-keyboards/mouse-pad/signo-wrist-pad-zuplex-wr-500-black-8932116573050_d8206y",
        "image": "https://media-cdn.bnn.in.th/131060/Signo-Wrist-Pad-Zuplex-WR-500-Black-03-square_medium.jpg",
        "spec": { "dimension": "44.0 x 9.5 x 1.8 cm.", "material": "Rubber" }
      }
    ]
  },
  {
    "model": "prismcloth",
    "name": "STEELSERIES GAMING MOUSE PAD PRISM CLOTH",
    "store": "Banana",
    "brand": "Steelseries",
    "category": "Mousepad",
    "tag": "Gaming",
    "data": [
      {
        "name": "STEELSERIES GAMING MOUSE PAD PRISM CLOTH M SIZE BLACK",
        "price": 1390,
        "href": "https://www.bnn.in.th/th/p/gaming-gear/pc-gaming-accessories/gaming-mouse-pad/steelseries-gaming-mouse-pad-prism-cloth-m-size-black-5707119036795_rqyjvz",
        "image": "https://media-cdn.bnn.in.th/41895/SteelSeries-Gaming-Mouse-Pad-Prism-Cloth-M-Black-3-square_medium.jpg",
        "spec": { "dimension": "32 x 27 x 4 cm.", "material": "Silicon Rubber" }
      }
    ]
  },
  {
    "model": "prismcloth",
    "name": "STEELSERIES GAMING MOUSE PAD PRISM CLOTH",
    "store": "Banana",
    "brand": "Steelseries",
    "category": "Mousepad",
    "tag": "Gaming",
    "data": [
      {
        "name": "STEELSERIES GAMING MOUSE PAD PRISM CLOTH XL SIZE",
        "price": 2590,
        "href": "https://www.bnn.in.th/th/p/gaming-gear/pc-gaming-accessories/gaming-mouse-pad/steelseries-gaming-mouse-pad-prism-cloth-xl-size-5707119036818_d838lz",
        "image": "https://media-cdn.bnn.in.th/41897/Steelseries-Gaming-Mouse-Pad-Prism-Cloth-Size-XL-1-square_medium.jpg",
        "spec": {
          "dimension": "90 x 0.4 x 30 cm.",
          "material": "Silicon Rubber"
        }
      }
    ]
  },
  {
    "model": "qckedge",
    "name": "STEELSERIES GAMING MOUSE PAD QCK EDGE",
    "store": "Banana",
    "brand": "Steelseries",
    "category": "Mousepad",
    "tag": "Gaming",
    "data": [
      {
        "name": "STEELSERIES GAMING MOUSE PAD QCK EDGE L SIZE",
        "price": 673,
        "href": "https://www.bnn.in.th/th/p/gaming-gear/pc-gaming-accessories/gaming-mouse-pad/steelseries-gaming-mouse-pad-qck-edge-l-size-5707119036757_zg925d",
        "image": "https://media-cdn.bnn.in.th/41875/SteelSeries-Gaming-Mouse-Pad-QcK-Edge-L-Size-3-square_medium.jpg",
        "spec": {
          "dimension": "45 x 40 x 0.2 cm.",
          "material": "Silicon Rubber"
        }
      }
    ]
  },
  {
    "model": "qckedge",
    "name": "STEELSERIES GAMING MOUSE PAD QCK EDGE",
    "store": "Banana",
    "brand": "Steelseries",
    "category": "Mousepad",
    "tag": "Gaming",
    "data": [
      {
        "name": "STEELSERIES GAMING MOUSE PAD QCK EDGE M SIZE",
        "price": 540,
        "href": "https://www.bnn.in.th/th/p/gaming-gear/pc-gaming-accessories/gaming-mouse-pad/steelseries-gaming-mouse-pad-qck-edge-m-size-5707119036733_d4vg5d",
        "image": "https://media-cdn.bnn.in.th/41867/SteelSeries-Gaming-Mouse-Pad-QcK-Edge-M-Size-3-square_medium.jpg",
        "spec": {
          "dimension": "32 x 27 x 0.2 cm.",
          "material": "Silicon Rubber"
        }
      }
    ]
  },
  {
    "model": "gtfx",
    "name": "ZOWIE GAMING MOUSE PAD G TF- X",
    "store": "Banana",
    "brand": "Zowie",
    "category": "Mousepad",
    "tag": "Gaming",
    "data": [
      {
        "name": "ZOWIE GAMING MOUSE PAD G TF- X (L)",
        "price": 1190,
        "href": "https://www.bnn.in.th/th/p/gaming-gear/pc-gaming-accessories/gaming-mouse-pad/zowie-gaming-mouse-pad-g-tf-x-l-4718755062650_zp6ped",
        "image": "https://media-cdn.bnn.in.th/28045/ZOWIE-Gaming-Mouse-Pad-G-TF-x(L)-3-square_medium.jpg",
        "spec": { "dimension": "4.7 x 3.9 x 0.35 cm.", "material": "N/A" }
      }
    ]
  }
]
